MANIFEST.in
setup.py
dzenlog_link/__init__.py
dzenlog_link/admin.py
dzenlog_link/models.py
dzenlog_link/urls.py
dzenlog_link/views.py
dzenlog_link.egg-info/PKG-INFO
dzenlog_link.egg-info/SOURCES.txt
dzenlog_link.egg-info/dependency_links.txt
dzenlog_link.egg-info/not-zip-safe
dzenlog_link.egg-info/requires.txt
dzenlog_link.egg-info/top_level.txt
dzenlog_link/migrations/0001_initial.py
dzenlog_link/migrations/__init__.py
dzenlog_link/templates/dzenlog_link/body_detail.html
dzenlog_link/templates/dzenlog_link/body_list.html
dzenlog_link/templates/dzenlog_link/detail.html
dzenlog_link/templates/dzenlog_link/list.html
