Metadata-Version: 1.0
Name: dzenlog-link
Version: 0.1.2
Summary: This is a simple application to post links to the dzenlog.
Home-page: http://github.com/svetlyak40wt/django-dzenlog-link/
Author: Alexander Artemenko
Author-email: svetlyak.40wt@gmail.com
License: New BSD License
Keywords: django apps blogging dzenlog
Platform: UNKNOWN
Classifier: Development Status :: 3 - Alpha
Classifier: Environment :: Plugins
Classifier: Framework :: Django
Classifier: Intended Audience :: Developers
Classifier: License :: OSI Approved :: BSD License
Classifier: Programming Language :: Python
Classifier: Topic :: Software Development :: Libraries :: Python Modules
